reploncli/__init__.py
reploncli/reploncli.py
reploncli-0.9.4.dist-info/LICENSE
reploncli-0.9.4.dist-info/WHEEL
reploncli-0.9.4.dist-info/METADATA
reploncli-0.9.4.dist-info/RECORD
