Metadata-Version: 2.1
Name: reploncli
Version: 0.9.4
Summary: REPL extension to CLI apps
Home-page: https://github.com/silkyanteater/reploncli
License: MIT
Keywords: repl,cli,command line
Author: silkyanteater
Author-email: cyclopesrufus@gmail.com
Requires-Python: >=3.6,<4.0
Classifier: License :: OSI Approved :: MIT License
Classifier: Programming Language :: Python :: 3
Classifier: Programming Language :: Python :: 3.10
Classifier: Programming Language :: Python :: 3.6
Classifier: Programming Language :: Python :: 3.7
Classifier: Programming Language :: Python :: 3.8
Classifier: Programming Language :: Python :: 3.9
Project-URL: Repository, https://github.com/silkyanteater/reploncli
